leviosapy
