Metadata-Version: 2.1
Name: leviosapy
Version: 0.1.3
Summary: AsyncIO compatible library to talk to a Leviosa Motor Shades Zone
Home-page: https://github.com/greg-ha-1990/leviosapy
Download-URL: https://github.com/greg-ha-1990/leviosapy/archive/refs/tags/0.1.3.tar.gz
Author: Gerardo Castillo
Author-email: gcastillo@integrahome.net
License: APACHE 2.0
Keywords: Communication,AsyncIO,Leviosa Zone
Classifier: Development Status :: 5 - Production/Stable
Classifier: Intended Audience :: Developers
Classifier: Topic :: Software Development :: Build Tools
Classifier: License :: OSI Approved :: Apache Software License
Classifier: Programming Language :: Python :: 3.6
Classifier: Programming Language :: Python :: 3.7
Classifier: Programming Language :: Python :: 3.8
Classifier: Programming Language :: Python :: 3.9
Classifier: Programming Language :: Python :: 3.10
Classifier: Programming Language :: Python :: 3.11
License-File: LICENSE
